pydetectgpt/__init__.py
pydetectgpt/cli.py
pydetectgpt/detect.py
pydetectgpt/methods.py
pydetectgpt/utils.py
pydetectgpt-0.1.1.dist-info/LICENSE
pydetectgpt-0.1.1.dist-info/METADATA
pydetectgpt-0.1.1.dist-info/WHEEL
pydetectgpt-0.1.1.dist-info/entry_points.txt
pydetectgpt-0.1.1.dist-info/top_level.txt
pydetectgpt-0.1.1.dist-info/RECORD
