Metadata-Version: 2.1
Name: pydetectgpt
Version: 0.1.1
Summary: Easy to use Python library for detecting AI-generated text
Author-email: Dylan Harden <dylanharden33@gmail.com>
License: MIT License
Project-URL: Homepage, https://github.com/Dylan-Harden3/PyDetectGPT
Project-URL: Repository, https://github.com/Dylan-Harden3/PyDetectGPT
Keywords: ai,detection,llm,pytorch
Classifier: Development Status :: 3 - Alpha
Classifier: Intended Audience :: Science/Research
Classifier: License :: OSI Approved :: MIT License
Classifier: Programming Language :: Python :: 3
Classifier: Programming Language :: Python :: 3.8
Classifier: Programming Language :: Python :: 3.9
Classifier: Programming Language :: Python :: 3.10
Classifier: Programming Language :: Python :: 3.11
Requires-Python: >=3.8
License-File: LICENSE
Requires-Dist: torch
Requires-Dist: numpy
Requires-Dist: transformers
Provides-Extra: dev
Requires-Dist: black; extra == "dev"
Requires-Dist: ruff; extra == "dev"
Requires-Dist: pydocstyle; extra == "dev"
Requires-Dist: pytest; extra == "dev"
Requires-Dist: pytest-cov; extra == "dev"
